{"_START_": {"Bonjour": 2, "Bonsoir": 1, "\u00e7": 1, ":slightly_smiling_face:": 1, ":heart:": 1, "f": 1, "salut": 3, "yo": 4, "bonjour": 1, "tre": 1, "blbl": 1, "apzoeityuapzoierutapoizertypoizeru": 1, "apozeityaprytoizeyrtoiuzyert": 1, "go": 4, "\u00e7a": 1, "Salut": 3, "Yo": 1, "Coucou": 1, "oui": 1, "sony": 1, "Tu": 3, "C'est": 2, "_NICK_": 16, "WTF": 1, "il": 2, "Le": 2, "je": 1, "c'est": 2, "pas": 1, "maison": 1, "<@U8K1Z3CRM>": 1, "Non": 2, "En": 1, "Presque": 1, "mais": 1, "pourquoi": 1, "Il": 2, "<http://randomBot.com|randomBot.com>": 1, "raciste": 1, "parce": 1, "Je": 1, "<@U7UA6FUDR>": 1}, "Bonjour": {"_END_": 1, "_NICK_": 1}, "Bonsoir": {"_END_": 1}, "\u00e7": {"_NICK_": 1}, "_NICK_": {"_END_": 19, "?": 1, "music": 3, "\u00e7a": 2, "tarlouse": 1, "tu": 3, "c'est": 1, "comment": 1, "Ah": 1, "t'es": 1, "toi": 1, "Apprends": 1, "caca": 2}, ":slightly_smiling_face:": {"_NICK_": 1}, ":heart:": {"_NICK_": 1}, "f": {"_NICK_": 1}, "salut": {"_END_": 1, "_NICK_": 1, "bro": 1}, "yo": {"_NICK_": 2, "<@U7UG5HLLV>": 2}, "bro": {"_END_": 1}, "<@U7UG5HLLV>": {"_END_": 5}, "bonjour": {"<@U7UG5HLLV>": 1, "?": 1}, "tre": {"<@U7UG5HLLV>": 1}, "blbl": {"<@U7UG5HLLV>": 1}, "apzoeityuapzoierutapoizertypoizeru": {"_NICK_": 1}, "apozeityaprytoizeyrtoiuzyert": {"_NICK_": 1}, "go": {"_NICK_": 4}, "\u00e7a": {"va": 2, "c'est": 1}, "va": {"?": 2, "finir": 1, "rester": 1}, "?": {"_END_": 10, "xD": 1, "Ou": 1, ":thinking_face:": 1, ":stuck_out_tongue:": 1}, "Salut": {"_NICK_": 2, "_END_": 1}, "Yo": {"_END_": 1}, "Coucou": {"_NICK_": 1}, "oui": {"et": 1, "!": 1}, "et": {"toi": 1}, "toi": {"?": 1, "pas": 1, "y": 1, "devenir": 1}, "sony": {"music": 1}, "music": {"dub": 3, "tzer": 1}, "dub": {"_END_": 3}, "Tu": {"dis": 2, "ne": 1}, "dis": {"n'importe": 2, "toujours": 1, "ton": 1, "autre": 1, "ta": 1}, "n'importe": {"quoi": 1, "quoi,": 1}, "quoi": {"_NICK_": 1, "ta": 1, "?": 1}, "C'est": {"l'heure": 1, "pas": 1}, "l'heure": {"de": 1}, "de": {"la": 2, "google": 1}, "la": {"pause": 1, "m\u00eame": 1, "d\u00e9ja": 1, "bi\u00e8re": 1, "connais": 1, "cha\u00eene": 2}, "pause": {"_NICK_": 1}, "toujours": {"la": 1}, "m\u00eame": {"chose": 1, "pas": 1, "genre": 1}, "chose": {"_END_": 1, "que": 1}, "ne": {"r\u00e9ponds": 1}, "r\u00e9ponds": {"que": 1}, "que": {"si": 1, "bonjour": 1, "dis": 1, "d'apr\u00e8s": 1}, "si": {"je": 1, "tu": 1}, "je": {"dis": 1, "la": 1}, "ton": {"pr\u00e9nom": 1}, "pr\u00e9nom": {"_NICK_": 1}, "tzer": {"_END_": 1}, "WTF": {"?": 1}, "xD": {"_END_": 1}, "il": {"parle": 1, "est": 1, "r\u00e9pond": 1, "va": 1}, "parle": {"quelle": 1}, "quelle": {"langue": 1}, "langue": {"?": 1}, "Le": {"bot": 1, "pauvre": 1}, "bot": {"i": 1, "c'est": 1, "con": 1, "de": 1}, "i": {"la": 1}, "d\u00e9ja": {"fait": 1}, "fait": {"la": 1, "si": 1}, "bi\u00e8re": {"_END_": 1, "pr\u00e9f\u00e9r\u00e9e": 1}, "est": {"bien": 1}, "bien": {"bourr\u00e9": 1}, "bourr\u00e9": {"_END_": 1, "?": 1}, "tarlouse": {"_END_": 1}, "tu": {"dis": 1, "es": 1, "parles": 1, "lui": 1, "aimes": 1}, "autre": {"chose": 1}, "c'est": {"quoi": 1, "pas": 2, "un": 1, "slackbot": 1, "m\u00eame": 1, "devenir": 1}, "ta": {"bi\u00e8re": 1, "m\u00e8re?": 1, "m\u00e8re": 1}, "pr\u00e9f\u00e9r\u00e9e": {"?": 1}, "connais": {"pas": 1}, "pas": {"celle": 1, "un": 1, "loin": 1, "ou": 1, "non": 1, "francais": 1, "ce": 1, "le": 1}, "celle": {"l\u00e0": 1}, "l\u00e0": {"!": 1, "_END_": 1}, "!": {"_END_": 4}, "un": {"bot": 2, "/rand": 1}, "/rand": {"_END_": 1}, "comment": {"s'appelle": 1}, "s'appelle": {"ta": 1}, "m\u00e8re?": {"_END_": 1}, "es": {"un": 1}, "con": {"!": 1, "celui": 1, "?": 1}, "loin": {"_END_": 1}, "Ah": {"mais": 1}, "mais": {"tu": 1, "quoi": 1, "oui": 1, "_END_": 1}, "parles": {"france": 1}, "france": {"toi": 1}, "ou": {"pas": 1}, "non": {"mais": 1}, "Ou": {"mais": 1}, "maison": {"_END_": 1}, "<@U8K1Z3CRM>": {"a": 1}, "a": {"rejoint": 1, "vouloir": 1, "d\u00e9fini": 1}, "rejoint": {"la": 1}, "cha\u00eene": {"_END_": 1, ":": 1}, "t'es": {"bourr\u00e9": 1}, "Non": {"_NICK_": 1, "il": 1}, "slackbot": {"_END_": 1}, "En": {"fait": 1}, "lui": {"dis": 1}, "quoi,": {"il": 1}, "r\u00e9pond": {"des": 1}, "des": {"phrases": 1}, "phrases": {"qui": 1}, "qui": {"ont": 1}, "ont": {"du": 1}, "du": {"sens": 1}, "sens": {"?": 1}, ":thinking_face:": {"_END_": 1}, "Presque": {"_END_": 1}, "y": {"en": 1}, "en": {"a": 1}, "vouloir": {"c\u00e2ble": 1}, "c\u00e2ble": {"dans": 1}, "dans": {"prise": 1}, "prise": {"arri\u00e8re": 1}, "arri\u00e8re": {"?": 1}, "aimes": {"les": 1}, "les": {"frites": 1, "mots": 1}, "frites": {"?": 1}, "pourquoi": {"c'est": 1}, "francais": {"x)": 1}, "x)": {"_END_": 1}, "Il": {"apprend": 1, "va": 1}, "apprend": {"!": 1}, "<http://randomBot.com|randomBot.com>": {"_END_": 1}, "Apprends": {"les": 1}, "mots": {"importants": 1}, "importants": {"Zizi": 1}, "Zizi": {"Caca": 1}, "Caca": {"bite": 1}, "bite": {"prout": 1}, "prout": {"_END_": 1}, "ce": {"que": 1}, "m\u00e8re": {"_END_": 1}, "finir": {"comme": 1}, "comme": {"le": 1}, "le": {"bot": 1, "m\u00eame": 1, "kill": 1, "th\u00e8me": 1}, "google": {"_END_": 1}, "raciste": {"_END_": 1}, "caca": {"_END_": 1, "chez": 1}, "rester": {"con": 1}, "celui": {"l\u00e0": 1}, "chez": {"paul": 1}, "paul": {"_END_": 1}, "parce": {"que": 1}, "d'apr\u00e8s": {"toi": 1}, "devenir": {"nazi": 1, "moins": 1}, "nazi": {"c'est": 1}, "moins": {"con": 1}, ":stuck_out_tongue:": {"_END_": 1}, "genre": {"_END_": 1}, "Je": {"le": 1}, "kill": {"_END_": 1}, "pauvre": {"_END_": 1}, "<@U7UA6FUDR>": {"a": 1}, "d\u00e9fini": {"le": 1}, "th\u00e8me": {"de": 1}, ":": {"BOUARE": 1}, "BOUARE": {"_END_": 1}}